pod_base/__init__.py
pod_base/base.py
pod_base/config.ini
pod_base/config.py
pod_base/exceptions.py
pod_base/json_schema.py
pod_base/request.py
pod_base/servicecall.py
pod_base/version.py
pod_base-1.0.3.dist-info/LICENSE
pod_base-1.0.3.dist-info/METADATA
pod_base-1.0.3.dist-info/WHEEL
pod_base-1.0.3.dist-info/top_level.txt
pod_base-1.0.3.dist-info/RECORD
